electricitymaps/__init__.py
electricitymaps/client.py
electricitymaps/config.py
electricitymaps/py.typed
electricitymaps/adapters/__init__.py
electricitymaps/adapters/carbon_free_energy.py
electricitymaps/adapters/carbon_intensity.py
electricitymaps/adapters/default.py
electricitymaps/adapters/net_load.py
electricitymaps/adapters/optimize.py
electricitymaps/adapters/power_breakdown.py
electricitymaps/adapters/price_day_ahead.py
electricitymaps/adapters/renewable_energy.py
electricitymaps/adapters/total_load.py
openapi/__init__.py
openapi/api_client.py
openapi/api_response.py
openapi/configuration.py
openapi/exceptions.py
openapi/py.typed
openapi/rest.py
openapi/api/__init__.py
openapi/api/carbon_free_energy_api.py
openapi/api/carbon_intensity_api.py
openapi/api/default_api.py
openapi/api/net_load_api.py
openapi/api/power_breakdown_api.py
openapi/api/price_day_ahead_api.py
openapi/api/renewable_energy_api.py
openapi/api/total_load_api.py
openapi/models/__init__.py
openapi/models/carbon_intensity.py
openapi/models/carbon_intensity_forecast_query.py
openapi/models/carbon_intensity_forecast_response.py
openapi/models/carbon_intensity_forecast_response_forecast_inner.py
openapi/models/consumption_optimizer_params.py
openapi/models/consumption_optimizer_response.py
openapi/models/consumption_optimizer_response_optimization_output.py
openapi/models/data_center_location.py
openapi/models/emission_factor_type.py
openapi/models/energy_share.py
openapi/models/energy_share_forecast_query.py
openapi/models/energy_share_forecast_response.py
openapi/models/forecast_environment.py
openapi/models/history_query.py
openapi/models/history_response_carbon_intensity.py
openapi/models/history_response_energy_share.py
openapi/models/history_response_load.py
openapi/models/history_response_power_breakdown.py
openapi/models/history_response_price_day_ahead.py
openapi/models/input_error.py
openapi/models/latest_query.py
openapi/models/load.py
openapi/models/load_forecast_query.py
electricitymaps-0.0.1.dist-info/METADATA
electricitymaps-0.0.1.dist-info/WHEEL
electricitymaps-0.0.1.dist-info/top_level.txt
electricitymaps-0.0.1.dist-info/RECORD
