Metadata-Version: 2.4
Name: electricitymaps
Version: 0.0.1
Summary: Official Electricity Maps Python SDK
Home-page: https://github.com/electricitymaps/electricitymaps-contrib
Author: Electricity Maps
Author-email: Electricity Maps <hello@electricitymaps.com>
License: MIT
Project-URL: Documentation, https://docs.electricitymaps.com
Project-URL: Source, https://github.com/electricitymaps/electricitymaps-contrib
Project-URL: Tracker, https://github.com/electricitymaps/electricitymaps-contrib/issues
Keywords: OpenAPI,Electricity Maps API,carbon intensity,SDK
Requires-Python: >=3.10
Requires-Dist: urllib3<3.0.0,>=2.1.0
Requires-Dist: python-dateutil>=2.8.2
Requires-Dist: pydantic>=2
Requires-Dist: typing-extensions>=4.7.1
Dynamic: author
Dynamic: home-page
Dynamic: requires-python
